module3/fifo_controller.v
module fifo_controller #(parameter FIFO_ASIZE = 4) 
(
  input  wire in_clock,
  input  wire in_reset,         
  input  wire in_take,
  input  wire in_put,
  output wire out_empty,
  output wire out_full,
  output wire[FIFO_ASIZE-1:0] out_write_pointer,
  output wire[FIFO_ASIZE-1:0] out_read_pointer
);
  
  reg[FIFO_ASIZE:0] write_counter;
  reg[FIFO_ASIZE:0] read_counter;

  assign out_empty = (write_counter == read_counter);

  assign out_full  = (write_counter[FIFO_ASIZE] != read_counter[FIFO_ASIZE]) &&
                   (write_counter[FIFO_ASIZE-1:0] == read_counter[FIFO_ASIZE-1:0]);

  assign out_write_pointer = write_counter[FIFO_ASIZE-1:0];
  assign out_read_pointer  = read_counter[FIFO_ASIZE-1:0];
  
  always @(posedge in_clock) begin
    if (in_reset) begin
      write_counter <= 0;
      read_counter <= 0;
    end else begin
      if (in_put && !out_full) begin
        write_counter = write_counter + 1;
      end
      if (in_take && !out_empty) begin
        read_counter = read_counter + 1;
      end
    end
  end
endmodule

module3/tb_fifo_controller.v
`default_nettype none
`timescale 1ns/1ns

module tb_fifo_controller;
// DUT simulation signals
  reg in_clock;
  reg in_reset;
  reg in_take;
  reg in_put;

  wire out_empty;
  wire out_full;
  wire [3:0] out_write_pointer;
  wire [3:0] out_read_pointer;

  wire [2:0] i_nets;
  wire [1:0] o_nets;

  assign i_nets = {in_take, in_put, in_reset};
  assign o_nets = {out_empty, out_full};

  // Device under test
  fifo_controller
  DUT
  (
   .in_clock(in_clock), 
   .in_reset(in_reset), 
   .in_take(in_take), 
   .in_put(in_put), 

   .out_empty(out_empty), 
   .out_full(out_full), 
   .out_write_pointer(out_write_pointer), 
   .out_read_pointer(out_read_pointer)
  );

  initial in_clock = 1;
  always #1 in_clock = ~in_clock;

  // the main simulation
  initial begin
      $monitor("Time=%4t | Reset=%b | Put=%b Take=%b | Empty=%b Full=%b | W_Ptr=%d R_Ptr=%d", 
               $time, in_reset, in_put, in_take, out_empty, out_full, out_write_pointer, out_read_pointer);
      $dumpfile("tb_fifo_controller.vcd");
      $dumpvars(0, tb_fifo_controller);

      // Initial State
      in_reset = 0;
      in_put   = 0;
      in_take  = 0;

      // 1. Trigger Reset
      #(2);
      in_reset = 1;
      #(2); // Hold for a full clock cycle
      in_reset = 0;
      #(2);

      // 2. Fill the FIFO (ASIZE=4 means 16 slots)
      $display("--- Starting Fill Operation ---");
      in_put = 1;
      repeat (16) @(posedge in_clock);
      
      // At this point, out_full should be 1
      in_put = 0;
      #(4);

      // 3. Try to 'Put' into a Full FIFO (should have no effect)
      in_put = 1;
      #(2);
      in_put = 0;

      // 4. Empty the FIFO
      $display("--- Starting Empty Operation ---");
      in_take = 1;
      repeat (16) @(posedge in_clock);
      
      // At this point, out_empty should be 1
      in_take = 0;
      #(10);

      $finish;
    end

endmodule

module3/tb_fifo_controller.vcd
$date
	Sat Jan 31 10:48:14 2026
$end
$version
	Icarus Verilog
$end
$timescale
	1ns
$end
$scope module tb_fifo_controller $end
$var wire 4 ! out_write_pointer [3:0] $end
$var wire 4 " out_read_pointer [3:0] $end
$var wire 1 # out_full $end
$var wire 1 $ out_empty $end
$var wire 2 % o_nets [1:0] $end
$var wire 3 & i_nets [2:0] $end
$var reg 1 ' in_clock $end
$var reg 1 ( in_put $end
$var reg 1 ) in_reset $end
$var reg 1 * in_take $end
$scope module DUT $end
$var wire 1 ' in_clock $end
$var wire 1 ( in_put $end
$var wire 1 ) in_reset $end
$var wire 1 * in_take $end
$var wire 1 # out_full $end
$var wire 4 + out_write_pointer [3:0] $end
$var wire 4 , out_read_pointer [3:0] $end
$var wire 1 $ out_empty $end
$var parameter 32 - FIFO_ASIZE $end
$var reg 5 . read_counter [4:0] $end
$var reg 5 / write_counter [4:0] $end
$upscope $end
$upscope $end
$enddefinitions $end
$comment Show the parameter values. $end
$dumpall
b100 -
$end
#0
$dumpvars
bx /
bx .
bx ,
bx +
0*
0)
0(
1'
b0 &
bx %
x$
x#
bx "
bx !
$end
#1
0'
#2
0#
b10 %
b0 "
b0 ,
b0 !
b0 +
1$
b0 .
b0 /
b1 &
1'
1)
#3
0'
#4
b0 &
1'
0)
#5
0'
#6
b0 %
b1 !
b1 +
0$
b1 /
b10 &
1'
1(
#7
0'
#8
b10 !
b10 +
b10 /
1'
#9
0'
#10
b11 !
b11 +
b11 /
1'
#11
0'
#12
b100 !
b100 +
b100 /
1'
#13
0'
#14
b101 !
b101 +
b101 /
1'
#15
0'
#16
b110 !
b110 +
b110 /
1'
#17
0'
#18
b111 !
b111 +
b111 /
1'
#19
0'
#20
b1000 !
b1000 +
b1000 /
1'
#21
0'
#22
b1001 !
b1001 +
b1001 /
1'
#23
0'
#24
b1010 !
b1010 +
b1010 /
1'
#25
0'
#26
b1011 !
b1011 +
b1011 /
1'
#27
0'
#28
b1100 !
b1100 +
b1100 /
1'
#29
0'
#30
b1101 !
b1101 +
b1101 /
1'
#31
0'
#32
b1110 !
b1110 +
b1110 /
1'
#33
0'
#34
b1111 !
b1111 +
b1111 /
1'
#35
0'
#36
b1 %
1#
b0 &
b0 !
b0 +
0(
b10000 /
1'
#37
0'
#38
1'
#39
0'
#40
b10 &
1'
1(
#41
0'
#42
b0 %
0#
b1 "
b1 ,
b1 .
b100 &
1'
1*
0(
#43
0'
#44
b10 "
b10 ,
b10 .
1'
#45
0'
#46
b11 "
b11 ,
b11 .
1'
#47
0'
#48
b100 "
b100 ,
b100 .
1'
#49
0'
#50
b101 "
b101 ,
b101 .
1'
#51
0'
#52
b110 "
b110 ,
b110 .
1'
#53
0'
#54
b111 "
b111 ,
b111 .
1'
#55
0'
#56
b1000 "
b1000 ,
b1000 .
1'
#57
0'
#58
b1001 "
b1001 ,
b1001 .
1'
#59
0'
#60
b1010 "
b1010 ,
b1010 .
1'
#61
0'
#62
b1011 "
b1011 ,
b1011 .
1'
#63
0'
#64
b1100 "
b1100 ,
b1100 .
1'
#65
0'
#66
b1101 "
b1101 ,
b1101 .
1'
#67
0'
#68
b1110 "
b1110 ,
b1110 .
1'
#69
0'
#70
b1111 "
b1111 ,
b1111 .
1'
#71
0'
#72
0#
b0 &
b10 %
b0 "
b0 ,
0*
1$
b10000 .
1'
