module2/edge_counter.v
module edge_detector(
  input wire in_clock,
  input wire in_signal,
  output wire out_strobe
);

  reg asserted = 0;
  always @(posedge in_clock) begin
    asserted <= in_signal;
  end

  assign out_strobe = ~asserted & in_signal;
endmodule

module counter(
  input wire in_clock,
  input wire in_reset,
  input wire in_enable,

  output reg [7:0] out_value
);

  always @(posedge in_clock) begin 
    out_value <= in_reset ? 0 : out_value + in_enable;
  end

endmodule

module edge_counter(
  input wire in_clock,
  input wire in_reset,
  input wire in_signal,
  output wire out_pulse,
  output wire [7:0] out_count
);

  edge_detector u_edge_detector( in_clock, in_signal, out_pulse);
  counter u_counter( in_clock, in_reset, out_pulse, out_count);

endmodule

module2/tb_edge_counter.v
`default_nettype none
`timescale 1ns / 1ns

module tb_edge_counter;
  // DUT simulation signals
  reg in_clock;
  reg in_reset;
  reg in_signal;

  wire [2:0] in_nets;

  wire out_pulse;
  wire [7:0] out_value;

  assign in_nets = { in_clock, in_reset, in_signal};

  // Device Under Test
  edge_counter
  DUT
  (
    .in_clock(in_clock),
    .in_reset(in_reset),
    .in_signal(in_signal),
  
    .out_pulse(out_pulse),
    .out_count(out_value)
  );
 
  initial in_clock = 0;
  always #1 in_clock = ~in_clock;

  // The main simulation
  initial
  begin
    // Added output formatting
    $monitor("Time=%4t | Clock=%b | Inputs (Clk,Rst,En)=%b | Output=%d | Pulse=%b", 
             $time, in_clock, in_nets, out_value, out_pulse);
    $dumpfile("edge_counter.vcd");
    $dumpvars;
    $display;
    

    // Initialize inputs
    in_reset  = 1; // Start with reset active (assuming active high)
    in_signal = 0;

    // Wait for a few cycles, then release reset
    #2;
    in_reset  = 0;
    in_signal = 0;
    
    #4;
    in_signal = 1;

    #2;
    in_signal = 0;

    #6;
    in_signal = 1;

    // Run simulation for specific time
    #40;
    
    $finish; // End simulation
  end
endmodule

module2/edge_counter.vcd
$date
	Sat Jan 17 21:15:42 2026
$end
$version
	Icarus Verilog
$end
$timescale
	1ns
$end
$scope module tb_edge_counter $end
$var wire 8 ! out_value [7:0] $end
$var wire 1 " out_pulse $end
$var wire 3 # in_nets [2:0] $end
$var reg 1 $ in_clock $end
$var reg 1 % in_reset $end
$var reg 1 & in_signal $end
$scope module DUT $end
$var wire 1 $ in_clock $end
$var wire 1 % in_reset $end
$var wire 1 & in_signal $end
$var wire 1 " out_pulse $end
$var wire 8 ' out_count [7:0] $end
$scope module u_counter $end
$var wire 1 $ in_clock $end
$var wire 1 % in_reset $end
$var wire 1 " in_enable $end
$var reg 8 ( out_value [7:0] $end
$upscope $end
$scope module u_edge_detector $end
$var wire 1 $ in_clock $end
$var wire 1 & in_signal $end
$var wire 1 " out_strobe $end
$var reg 1 ) asserted $end
$upscope $end
$upscope $end
$upscope $end
$enddefinitions $end
$comment Show the parameter values. $end
$dumpall
$end
#0
$dumpvars
0)
bx (
bx '
0&
1%
0$
b10 #
0"
bx !
$end
#1
b0 !
b0 '
b0 (
b110 #
1$
#2
b0 #
0$
0%
#3
b100 #
1$
#4
b0 #
0$
#5
b100 #
1$
#6
b1 #
1"
0$
1&
#7
0"
b1 !
b1 '
b1 (
1)
b101 #
1$
#8
b0 #
0$
0&
#9
0)
b100 #
1$
#10
b0 #
0$
#11
b100 #
1$
#12
b0 #
0$
#13
b100 #
1$
#14
b1 #
1"
0$
1&
#15
0"
b10 !
b10 '
b10 (
1)
b101 #
1$
#16
b1 #
0$
#17
b101 #
1$
#18
b1 #
0$
#19
b101 #
1$
#20
b1 #
0$
#21
b101 #
1$
#22
b1 #
0$
#23
b101 #
1$
#24
b1 #
0$
#25
b101 #
1$
#26
b1 #
0$
#27
b101 #
1$
#28
b1 #
0$
#29
b101 #
1$
#30
b1 #
0$
#31
b101 #
1$
#32
b1 #
0$
#33
b101 #
1$
#34
b1 #
0$
#35
b101 #
1$
#36
b1 #
0$
#37
b101 #
1$
#38
b1 #
0$
#39
b101 #
1$
#40
b1 #
0$
#41
b101 #
1$
#42
b1 #
0$
#43
b101 #
1$
#44
b1 #
0$
#45
b101 #
1$
#46
b1 #
0$
#47
b101 #
1$
#48
b1 #
0$
#49
b101 #
1$
#50
b1 #
0$
#51
b101 #
1$
#52
b1 #
0$
#53
b101 #
1$
#54
b1 #
0$
